Workbook
Name a: #REF!
Name afg: '[1]Standard Country page'!#REF!
Name Weights: #REF!

Sheet WORKING VERSION
A1: Country | B1: Country Code (highlighted if ida-eligible country) | C1: IDA country | D1: NSDS Name | E1: NSDS Year | F1: Add URL | G1: last year | H1: last year raw | I1: needs to be checked/updated | J1: updated August 2025 (Yes/No) | K1: Is the NSDS accessible? | L1: Language (Fill in) | M1: Detailed budget available? (Yes/No) | N1: Gender data mentioned in budget (Yes/No) | O1: Are years listed in budget for gender? | P1: Gender in budget description (How is the line item for gender phrased? Entire table? Line item, other relevant descriptors) | Q1: Total gender budget number in currency of publication | R1: total gender budget currency iso code | S1: Line-item breakdown (if relevant, separated by semi-colon) | T1: Resource breakdown available for gender data or for entire plan? | U1: Domestic / External split | V1: State / Government | W1: Technical / Financial partners | X1: Other
A2: Aruba | B2: ABW | C2: =COUNTIF('IDA country list'!B$2:B$79,'WORKING VERSION'!B2) = 1 -> FALSE | D2: Not available | G2: =RIGHT(E2,4) | I2: =H2<2025 -> TRUE
A3: Afghanistan | B3: AFG | C3: =COUNTIF('IDA country list'!B$2:B$79,'WORKING VERSION'!B3) = 1 -> TRUE | I3: =H3<2025 -> TRUE | J3: TRUE
A4: Angola | B4: AGO | C4: =COUNTIF('IDA country list'!B$2:B$79,'WORKING VERSION'!B4) = 1 -> FALSE | D4: Plano Estatistico Nacional de Medio Prazo 2015-25 | E4: 2015-2025 | F4: https://www.ine.gov.ao/Arquivos/arquivosCarregados//Carregados/Publicacao_637873637947742390.pdf | G4: =RIGHT(E4,4) -> 2025 | H4: 2025 | I4: =H4<2025 -> FALSE | K4: No
A5: Anguilla | B5: AIA | C5: =COUNTIF('IDA country list'!B$2:B$79,'WORKING VERSION'!B5) = 1 -> FALSE | D5: Statistics Strategic Plan 2005-2009 | G5: =RIGHT(E5,4) | I5: =H5<2025 -> TRUE
A6: Albania | B6: ALB | C6: =COUNTIF('IDA country list'!B$2:B$79,'WORKING VERSION'!B6) = 1 -> FALSE | D6: Development Strategy of INSTAT 2017-2030 | E6: 2017-2030 | F6: http://www.instat.gov.al/media/3986/development-strategy-of-instat-2017-2030.pdf | G6: =RIGHT(E6,4) -> 2030 | H6: 2030 | I6: =H6<2025 -> FALSE | K6: Yes | L6: English | M6: No
A7: Andorra | B7: AND | C7: =COUNTIF('IDA country list'!B$2:B$79,'WORKING VERSION'!B7) = 1 -> FALSE | D7: llei 13/2022, del 12 de maig, del Pla d’estadística 2022-2025 | E7: 2022-2025 | F7: https://www.consellgeneral.ad/ca/activitat-parlamentaria/lleis-aprovades/llei-13-2022-del-12-de-maig-del-pla-d2019estadistica-2022-2025 | G7: =RIGHT(E7,4) -> 2025 | H7: 2025 | I7: =H7<2025 -> FALSE
A8: United Arab Emirates | B8: ARE | C8: =COUNTIF('IDA country list'!B$2:B$79,'WORKING VERSION'!B8) = 1 -> FALSE | D8: Not available | G8: =RIGHT(E8,4) | I8: =H8<2025 -> TRUE
A9: Argentina | B9: ARG | C9: =COUNTIF('IDA country list'!B$2:B$79,'WORKING VERSION'!B9) = 1 -> FALSE | D9: Plan Estratégico 2021-2026 | E9: 2021-2026 | F9: https://www.indec.gob.ar/ftp/cuadros/menusuperior/documentos-auxiliares/plan_estrategico_INDEC_2021_2026.pdf | G9: =RIGHT(E9,4) -> 2026 | H9: 2026 | I9: =H9<2025 -> FALSE | K9: Yes | L9: Spanish | M9: No
A10: Armenia | B10: ARM | C10: =COUNTIF('IDA country list'!B$2:B$79,'WORKING VERSION'!B10) = 1 -> FALSE | D10: Five year state statistical programme 2024-2028 | E10: 2024-2028 | F10: https://www.arlis.am/DocumentView.aspx?DocID=186099 | G10: =RIGHT(E10,4) -> 2028 | H10: 2028 | I10: =H10<2025 -> FALSE | K10: Yes | M10: No
A11: Antigua and Barbuda | B11: ATG | C11: =COUNTIF('IDA country list'!B$2:B$79,'WORKING VERSION'!B11) = 1 -> FALSE | D11: Not available | G11: =RIGHT(E11,4) | I11: =H11<2025 -> TRUE
A12: Australia | B12: AUS | C12: =COUNTIF('IDA country list'!B$2:B$79,'WORKING VERSION'!B12) = 1 -> FALSE | D12: ABS Corporate Plan 2024-25 | E12: 2024-2025 | F12: https://www.abs.gov.au/about/our-organisation/corporate-reporting/abs-corporate-plan/latest-release | G12: =RIGHT(E12,4) -> 2025 | H12: 2025 | I12: =H12<2025 -> FALSE | K12: Yes | L12: English | M12: No
A13: Austria | B13: AUT | C13: =COUNTIF('IDA country list'!B$2:B$79,'WORKING VERSION'!B13) = 1 -> FALSE | D13: Statistical Work Program 2021-2024 | F13: https://www.statistik.at/fileadmin/pages/535/strategie_2025.pdf | G13: =RIGHT(E13,4) | I13: =H13<2025 -> TRUE | K13: Yes | L13: German | M13: No
A14: Azerbaijan | B14: AZE | C14: =COUNTIF('IDA country list'!B$2:B$79,'WORKING VERSION'!B14) = 1 -> FALSE | D14: State Program on Improvement of the Official Statistics in the Republic of Azerbaijan 2018-2025 | E14: 2018-2025 | F14: https://www.stat.gov.az/menu/2/state_programs/2018_2025/source/en/2018-2025_DP_ENG.pdf | G14: =RIGHT(E14,4) -> 2025 | H14: 2025 | I14: =H14<2025 -> FALSE | K14: Yes | L14: English | M14: No
A15: Burundi | B15: BDI | C15: =COUNTIF('IDA country list'!B$2:B$79,'WORKING VERSION'!B15) = 1 -> TRUE | D15: Stratégie Nationale du Développement de la Statistique 2016-2020 | E15: 2016-2020 | F15: https://isteebu.bi/wp-content/uploads/2023/01/NSDS-Burundi_Document-Principal-2.pdf | G15: =RIGHT(E15,4) -> 2020 | H15: 2020 | I15: =H15<2025 -> TRUE | K15: Yes | L15: French | M15: Yes | N15: Yes | O15: Yes: 2016-2020 | P15: Line item: Disaggregation of all statistical data by province and gender (pg. 67) | Q15: 0 | R15: FBU | S15: $0 allocated, because goal was achieved in previous NSDS implementation
A16: Belgium | B16: BEL | C16: =COUNTIF('IDA country list'!B$2:B$79,'WORKING VERSION'!B16) = 1 -> FALSE | D16: Statistisch programma 2023 | E16: 2024 | F16: https://statbel.fgov.be/sites/default/files/Over_Statbel_FR/Programme%20statistique%20Statbel%202024-20221214-NL.pdf | G16: =RIGHT(E16,4) -> 2024 | H16: 2024 | I16: =H16<2025 -> TRUE | K16: Yes | L16: Dutch | M16: No
A17: Benin | B17: BEN | C17: =COUNTIF('IDA country list'!B$2:B$79,'WORKING VERSION'!B17) = 1 -> TRUE | D17: Stratégie Nationale de Développement de la Statistique 2020-23 | E17: 2020-2023 | F17: https://afristat.org/wp-content/uploads/2022/04/1_Benin-SNDS-2020-2023.pdf | G17: =RIGHT(E17,4) -> 2023 | H17: 2023 | I17: =H17<2025 -> TRUE | J17: TRUE | K17: Yes | L17: French | M17: Yes | N17: Yes | O17: Yes: 2020 to 2023 | P17: Activity 4 under Expected Results (RA) 2.2.2: Develop the Index on Development and Gender Inequalities in Benin (IDISB) (page 78 of PDF) | Q17: 14200000 | R17: FCFA | S17: Develop the Index on Development and Gender Inequalities in Benin (IDISB): 14.2 (Million FCFA) | T17: Yes
A18: Burkina Faso | B18: BFA | C18: =COUNTIF('IDA country list'!B$2:B$79,'WORKING VERSION'!B18) = 1 -> TRUE | D18: Schéma Directeur de la Statistique 2021-2025 | E18: 2021-2025 | F18: https://www.insd.bf/sites/default/files/2022-01/SDS-2021-2025.pdf | G18: =RIGHT(E18,4) -> 2025 | H18: 2025 | I18: =H18<2025 -> FALSE | K18: Yes | L18: French | M18: Yes | N18: Yes | O18: Yes: 2021-2025 | P18: 188- Develop gender booklets for the East, Center-East and Center-South; 193- Develop gender booklets for the regions of the Boucle du Mouhoun, Cascades, Hauts-Bassins, and South West; 198- Develop gender booklets for the Sahel and Center regions north; 202- Develop the gender booklet; 310- Develop the Women and Gender Directory; 311- Develop the Women and Gender dashboard; 425- Develop the directory of offenses involving minors and women during the police investigation phase; 426- Develop the dashboard of offenses involving minors and women during the police investigation phase; 449- Collect monitoring data on [...] women's busines in the regions of Boucle du Mouhoun and the East; 483- Carry out a census of associations/NGOs involved in the social action and women's sector; 492- Carry out a study on the socio-economic conditions of women in the region; 568- Ensure the dissemination on the INSD website of DSCVM publications (Social Dashboards, Gender Booklets....; 570- Ensure the distribution on the INSD website of the publications of the DR-INSD the DSSE (Statistical Yearbooks, gender booklets...); 617- Edit the women and gender dashboard; 620 Edit the report on the census of associations/NGOs working in the social action and women's sector; 658- Edit the directory of offenses involving minors and women during the police investigation phase; 659- Edit the dashboard of offenses involving minors and women during the police investigation phase | Q18: 683400000 | R18: FCFA | S18: 188- Develop gender booklets for the East, Center-East and Center-South: 25 million FCFA 193- Develop gender booklets for the regions of the Boucle du Mouhoun, Cascades, Hauts-Bassins, and South West: 24.4 million FCFA 198- Develop gender booklets for the Sahel and Center regions north: 9.6 million FCFA 202- Develop the gender booklet: 20 million FCFA 310- Develop the Women and Gender Directory: 55.5 million FCFA 311- Develop the Women and Gender dashboard: 60.3 million FCFA 425- Develop the directory of offenses involving minors and women during the police investigation phase: 100 million FCFA 426- Develop the dashboard of offenses involving minors and women during the police investigation phase: 25 million FCFA 449- Collect monitoring data on [...] women's busines in the regions of Boucle du Mouhoun and the East: 217.9 million FCFA 483- Carry out a census of associations/NGOs involved in the social action and women's sector: 87 million FCFA 492- Carry out a study on the socio-economic conditions of women in the region: 6.3 million FCFA 568- Ensure the dissemination on the INSD website of DSCVM publications (Social Dashboards, Gender Booklets....: 0 million FCFA 570- Ensure the distribution on the INSD website of the publications of the DR-INSD the DSSE (Statistical Yearbooks, gender booklets...): 0 million FCFA 617- Edit the women and gender dashboard: 9.4 million FCFA 620 Edit the report on the census of associations/NGOs working in the social action and women's sector: 3 million FCFA 658- Edit the directory of offenses involving minors and women during the police investigation phase: 20 million FCFA 659- Edit the dashboard of offenses involving minors and women during the police investigation phase 20 million FCFA | T18: TBD
A19: Bangladesh | B19: BGD | C19: =COUNTIF('IDA country list'!B$2:B$79,'WORKING VERSION'!B19) = 1 -> TRUE | D19: National Strategy for the Development of Statistics 2013-23 | E19: 2013-2023 | F19: http://www.paris21.org/sites/default/files/Bangladesh NSDS_2013-23_Final Cabinet approved.pdf | G19: =RIGHT(E19,4) -> 2023 | H19: 2023 | I19: =H19<2025 -> TRUE | J19: TRUE | K19: Yes | L19: English | M19: Yes | N19: Yes | O19: Yes: 2015 to 2023 | P19: Three gender-focused strategic goals in budget under the demography and health wing: Strategic goal 4: Monitoring the nutritional status of child and mother; Strategic goal 5: Gender statistics; Strategic goal 6: Violence against women (VAW). Each strategic goal has 3-4 detailed progress indicators (page 83). | Q19: 384000000 | R19: BDT | S19: Monitoring the nutrition status of child and mother: 350.00 (Million Taka); Gender statistics: 4.00 (Million Taka); VAW: 30.00 (Million Taka) (page 83)
A20: Bulgaria | B20: BGR | C20: =COUNTIF('IDA country list'!B$2:B$79,'WORKING VERSION'!B20) = 1 -> FALSE | D20: Strategy for Development of the National Statistical System 2021 - 2027 | E20: 2021-2027 | F20: https://www.nsi.bg/sites/default/files/files/pages/uplf_e/Strategy2021-2027_EN.pdf | G20: =RIGHT(E20,4) -> 2027 | H20: 2027 | I20: =H20<2025 -> FALSE | K20: Yes | L20: English | M20: No
A21: Bahrain | B21: BHR | C21: =COUNTIF('IDA country list'!B$2:B$79,'WORKING VERSION'!B21) = 1 -> FALSE | D21: Open Data Policy 2019-2023 | E21: 2019-2023 | F21: https://www.iga.gov.bh/Media/Pdf-Section/National%20Digital%20Policies/Open%20Data%20Policy%20V1.3.pdf | G21: =RIGHT(E21,4) -> 2023 | H21: 2023 | I21: =H21<2025 -> TRUE | K21: Yes | L21: English | M21: No
A22: The Bahamas | B22: BHS | C22: =COUNTIF('IDA country list'!B$2:B$79,'WORKING VERSION'!B22) = 1 -> FALSE | D22: Not available | G22: =RIGHT(E22,4) | I22: =H22<2025 -> TRUE
A23: Bosnia and Herzegovina | B23: BIH | C23: =COUNTIF('IDA country list'!B$2:B$79,'WORKING VERSION'!B23) = 1 -> FALSE | D23: Strategy for development of statistics 2021 - 2024 | E23: 2021-2024 | F23: https://bhas.gov.ba/data/Dokumenti/Planovi/STATISTICKI_PROGRAM_BIH_2021_2024.pdf | G23: =RIGHT(E23,4) -> 2024 | H23: 2024 | I23: =H23<2025 -> TRUE | K23: Yes | L23: Bosnian | M23: No
A24: Belarus | B24: BLR | C24: =COUNTIF('IDA country list'!B$2:B$79,'WORKING VERSION'!B24) = 1 -> FALSE | D24: Development of State Statistics of the Republic of Belarus 2017-2022 | E24: 2017-2022 | F24: https://www.belstat.gov.by/upload-belstat/upload-belstat-pdf/o-belstate/Stategija_2022-211025-en.pdf | G24: =RIGHT(E24,4) -> 2022 | H24: 2022 | I24: =H24<2025 -> TRUE | K24: Yes | L24: English | M24: No
A25: Belize | B25: BLZ | C25: =COUNTIF('IDA country list'!B$2:B$79,'WORKING VERSION'!B25) = 1 -> TRUE | D25: Belize's Second National Strategy for the Development of Statistics | E25: 2025-2029 | F25: https://sib.org.bz/wp-content/uploads/BelizeNSDSReport.pdf | G25: =RIGHT(E25,4) -> 2029 | H25: 2029 | I25: =H25<2025 -> FALSE | J25: TRUE | K25: Yes | L25: English | M25: Yes | N25: No
A26: Bolivia | B26: BOL | C26: =COUNTIF('IDA country list'!B$2:B$79,'WORKING VERSION'!B26) = 1 -> FALSE | D26: Plan Estratgégico Institucional PEI 2021-2025 | E26: 2021-2025 | F26: https://www.ine.gob.bo/index.php/descarga/715/plan-estrategico-institucional-2021-2025/59739/pei-2021-2025-del-ine.pdf | G26: =RIGHT(E26,4) -> 2025 | H26: 2025 | I26: =H26<2025 -> FALSE | K26: Yes | L26: Spanish | M26: Yes | N26: Yes | O26: Yes: 2021 to 2025 | P26: Line item, program category code to be defined - Comprehensive Survey on the Situation of Women (EISM) (page 53) | Q26: 10002257 | R26: BOB | S26: Comprehensive Survey on the Situation of Women (EISM): 10,002,257 (Bolivian Bolivianos) | T26: No
A27: Brazil | B27: BRA | C27: =COUNTIF('IDA country list'!B$2:B$79,'WORKING VERSION'!B27) = 1 -> FALSE | D27: PLANO Estratégico 2017 - 2027 | E27: 2017 - 2027 | F27: https://www.ibge.gov.br/np_download/novoportal/documentos_institucionais/Plano_Estrategico_2017_2027.pdf | G27: =RIGHT(E27,4) -> 2027 | H27: 2027 | I27: =H27<2025 -> FALSE | K27: Yes | L27: Portuguese | M27: No
A28: Barbados | B28: BRB | C28: =COUNTIF('IDA country list'!B$2:B$79,'WORKING VERSION'!B28) = 1 -> FALSE | D28: Not available | G28: =RIGHT(E28,4) | I28: =H28<2025 -> TRUE
A29: Brunei | B29: BRN | C29: =COUNTIF('IDA country list'!B$2:B$79,'WORKING VERSION'!B29) = 1 -> FALSE | D29: Not available | G29: =RIGHT(E29,4) | I29: =H29<2025 -> TRUE
A30: Bhutan | B30: BTN | C30: =COUNTIF('IDA country list'!B$2:B$79,'WORKING VERSION'!B30) = 1 -> TRUE | D30: National Strategy for the Development of Statistics 2024-229 | E30: 2024-2029 | F30: https://www.nsb.gov.bt/resources/plans/nsds/ | G30: =RIGHT(E30,4) -> 2029 | H30: 2029 | I30: =H30<2025 -> FALSE | J30: TRUE | K30: Yes | L30: English | M30: Yes | N30: No
A31: Botswana | B31: BWA | C31: =COUNTIF('IDA country list'!B$2:B$79,'WORKING VERSION'!B31) = 1 -> FALSE | D31: Botswana Strategy for the Development of Statistics 2015 – 2020 | E31: 2015-2020 | F31: http://www.paris21.org/sites/default/files/Botswana_Strategy_for_the_Development_of_Statistics__BSDS__-_2015_-_2020.pdf | G31: =RIGHT(E31,4) -> 2020 | H31: 2020 | I31: =H31<2025 -> TRUE | K31: Yes | L31: English | M31: Yes | N31: No
A32: Central African Republic | B32: CAF | C32: =COUNTIF('IDA country list'!B$2:B$79,'WORKING VERSION'!B32) = 1 -> TRUE | D32: Stratégie Nationale de développement de la statistique | E32: 2021-2025 | F32: https://afristat.org/wp-content/uploads/2022/04/6_RCA_SNDS-2021-2025-Finalisee.pdf | G32: =RIGHT(E32,4) -> 2025 | H32: 2025 | I32: =H32<2025 -> FALSE | K32: Yes | L32: French | M32: Yes | N32: Yes | O32: Yes: 2021-2025 | P32: Activity 3.1.1.1.B26: Conduct studies on target groups (children living and working on the street, child soldiers, the elderly, people with disabilities, OVC , victims of gender-based violence, etc.) (p.51); Activity 3.1.2.1: Take into account the needs for disaggregated data in the design and use of surveys and censuses. 2021-2025 (p. 52); Activity 3.1.2.2: Strengthen gender and regional data analysis (p. 52) | Q32: 337000000 | R32: FCFA | S32: Activity 3.1.1.1.B26: 250,000,000 FCFA; Activity 3.1.2.1: 21,000,000 FCFA; Activity 3.1.2.2: 66,000,000 FCFA | T32: Yes
A33: Canada | B33: CAN | C33: =COUNTIF('IDA country list'!B$2:B$79,'WORKING VERSION'!B33) = 1 -> FALSE | D33: Departmental Plan 2022–23 | E33: 2024-2025 | F33: https://www.statcan.gc.ca/en/transparency-accountability/corporate-management-reporting/departmental-plan/2024-2025 | G33: =RIGHT(E33,4) -> 2025 | H33: 2025 | I33: =H33<2025 -> FALSE | K33: Yes | L33: English | M33: No (broad budget but not broken down by activity/initiative) | N33: No | O33: Yes
A34: Switzerland | B34: CHE | C34: =COUNTIF('IDA country list'!B$2:B$79,'WORKING VERSION'!B34) = 1 -> FALSE | D34: Data Innovation Strategy 2017 | E34: 2017 | F34: https://www.bfs.admin.ch/bfs/en/home.assetdetail.3862240.html | G34: =RIGHT(E34,4) -> 2017 | H34: 2017 | I34: =H34<2025 -> TRUE | K34: Yes | L34: English | M34: No
A35: Chile | B35: CHL | C35: =COUNTIF('IDA country list'!B$2:B$79,'WORKING VERSION'!B35) = 1 -> FALSE | D35: Plan Estratégico Institucional 2018 - 2022 | E35: 2022-2026 | F35: https://www.ine.gob.cl/institutional/strategic-plan-2022-2026/strategic-objectives | G35: =RIGHT(E35,4) -> 2026 | H35: 2026 | I35: =H35<2025 -> FALSE | K35: Yes | L35: English (page translated) | M35: No
A36: China | B36: CHN | C36: =COUNTIF('IDA country list'!B$2:B$79,'WORKING VERSION'!B36) = 1 -> FALSE | D36: Not available | G36: =RIGHT(E36,4) | I36: =H36<2025 -> TRUE
A37: Cote d'Ivoire | B37: CIV | C37: =COUNTIF('IDA country list'!B$2:B$79,'WORKING VERSION'!B37) = 1 -> TRUE | D37: Stratégie nationale de développement de la statistique 2017 - 2021 | E37: 2017-2021 | F37: Not available | G37: =RIGHT(E37,4) -> 2021 | H37: 2021 | I37: =H37<2025 -> TRUE | J37: TRUE | K37: No | M37: Yes
A38: Cameroon | B38: CMR | C38: =COUNTIF('IDA country list'!B$2:B$79,'WORKING VERSION'!B38) = 1 -> TRUE | D38: Stratégie National de Développement de la Statistique (NSDS30, 2021-2030) 2021-2030 | E38: 2021-2030 | F38: https://www.afristat.org/wp-content/uploads/2023/06/SNDS30_Cameroun.pdf | G38: =RIGHT(E38,4) -> 2030 | H38: 2030 | I38: =H38<2025 -> FALSE | K38: Yes | L38: French | M38: Yes | N38: No. The strategic operation that gender is mentioned in is included, but because it is not broken down by specific sub-components, we cannot get a sense of how much budget is being devoted specifically to gender statistics activities (p.64). | O38: Yes: 2021-2025 | T38: No
A39: Congo, Dem. Rep. | B39: COD | C39: =COUNTIF('IDA country list'!B$2:B$79,'WORKING VERSION'!B39) = 1 -> TRUE | D39: Stratégie nationale de développement de la statistique 2012/13-17 | E39: 2012-2017 | F39: http://www.paris21.org/sites/default/files/DRC SNDS 2012-17.pdf | G39: =RIGHT(E39,4) -> 2017 | H39: 2017 | I39: =H39<2025 -> TRUE | J39: TRUE | K39: Yes | L39: French | M39: Yes | N39: No
A40: Congo, Rep. | B40: COG | C40: =COUNTIF('IDA country list'!B$2:B$79,'WORKING VERSION'!B40) = 1 -> TRUE | D40: Programme pluriannuel de développement de la statistique | E40: 2022-2026 | F40: https://www.afristat.org/wp-content/uploads/2023/06/SNDS_2022-2026_Congo.pdf | G40: =RIGHT(E40,4) -> 2026 | H40: 2026 | I40: =H40<2025 -> FALSE | K40: Yes | L40: French | M40: Yes | N40: Yes | O40: Yes: 2022-2026 | P40: A2O1R3: The production of gender statistics is promoted includes 3 line items - A2O1R3.1: awareness workshop on gender statistics; A2O1R3.2 development of a framework for producing gender statistics; A2O1R3.3: survey on gender-based violence (p.59) | Q40: 315000000 | R40: FCFA | S40: A2O1R3.1: 10,000,000 FCFA; A2O1R3.2: 5,000,000 FCFA; A2O1R3.3: 300,000,000 FCFA | T40: Yes
A41: Colombia | B41: COL | C41: =COUNTIF('IDA country list'!B$2:B$79,'WORKING VERSION'!B41) = 1 -> FALSE | D41: Plan Estadístico Nacional (PEN) 2023 - 2027 | E41: 2023-2027 | F41: https://www.sen.gov.co/sites/default/files/noticias-files/2023-12/plan_estadistico_naciona_2023-2027_0.pdf | G41: =RIGHT(E41,4) -> 2027 | H41: 2027 | I41: =H41<2025 -> FALSE | K41: Yes | L41: Spanish | M41: No
A42: Comoros | B42: COM | C42: =COUNTIF('IDA country list'!B$2:B$79,'WORKING VERSION'!B42) = 1 -> TRUE | I42: =H42<2025 -> TRUE | J42: TRUE
A43: Cabo Verde | B43: CPV | C43: =COUNTIF('IDA country list'!B$2:B$79,'WORKING VERSION'!B43) = 1 -> TRUE | D43: Estratégia Nacional de Desenvolvimento da Estatística (ENDE) | E43: 2022-2026 | F43: https://www.afristat.org/wp-content/uploads/2023/10/ENDE-2022_2026-VF.pdf | G43: =RIGHT(E43,4) -> 2026 | H43: 2026 | I43: =H43<2025 -> FALSE | K43: Yes | L43: Portuguese | M43: Yes | N43: Yes | O43: Yes: 2022-2026 | P43: Activity code: 3.2.1.02 Realizar o IV Inquérito Demográfico e de Saúde Reprodutiva (IDSR) | Q43: 201898899 | R43: CVE | S43: 3.2.1.02 Realizar o IV Inquérito Demográfico e de Saúde Reprodutiva (IDSR) 151279881; 3.2.2.15 Realizar o Inquérito Nacional sobre a Vulnerabilidade Alimentar e Nutricional das Famílias 40000000; 3.2.2.10 Realizar um inquérito ao ambiente e às mudanças climáticas junto à população/família 8779018; 3.2.2.14 Realizar Testes Diagnóstico ou Cognitivos nas Dimensões Não-Discriminação e Participação 1840000 | T43: No
A44: Costa Rica | B44: CRI | C44: =COUNTIF('IDA country list'!B$2:B$79,'WORKING VERSION'!B44) = 1 -> FALSE | D44: Plan Estadístico Nacional 2018 - 2022 | E44: 2023-2027 | F44: https://admin.sen.inec.cr/sites/default/files/2024-03/Documento%20PEN%202023%20-%202027.pdf | G44: =RIGHT(E44,4) -> 2027 | H44: 2027 | I44: =H44<2025 -> FALSE | K44: Yes | L44: Spanish | M44: Yes | N44: Yes | O44: End date: 30/6/19; End date: 30/6/19; End date: 31/12/18 | P44: Project PPI-03-01, disaggregation mentioned in description to address information gaps in statistical information (p.119); Project PPI-04-01 plan to strengthen administrative records, mention of increasing diversity of variables and more disaggregation of administrative units to improve records for statistical use (p.122); Project PPI-03-P4, gender mentioned in project description - sex-disaggregated employment and salary information databse activity (p.203) | Q44: Not Determined for either
A45: Cuba | B45: CUB | C45: =COUNTIF('IDA country list'!B$2:B$79,'WORKING VERSION'!B45) = 1 -> FALSE | D45: Not available | G45: =RIGHT(E45,4) | I45: =H45<2025 -> TRUE
A46: Cyprus | B46: CYP | C46: =COUNTIF('IDA country list'!B$2:B$79,'WORKING VERSION'!B46) = 1 -> FALSE | D46: Statistical Service of Cyprus Strategic Plan 2023-2025 | E46: 2023-2025 | F46: https://library.cystat.gov.cy/NEW/STRATEGIC_PLAN-2023_2025-EN-230223.pdf | G46: =RIGHT(E46,4) -> 2025 | H46: 2025 | I46: =H46<2025 -> FALSE | K46: Yes | L46: English | M46: No
A47: Czech Republic | B47: CZE | C47: =COUNTIF('IDA country list'!B$2:B$79,'WORKING VERSION'!B47) = 1 -> FALSE | D47: Strategic Plan of the Czech Statistical Office 2022-2026 | E47: 2022-2026 | F47: https://csu.gov.cz/docs/107516/11ff306a-4696-e27f-d221-60483b6038fe/czso_strategic_plan_2022_2026.pdf?version=1.0 | G47: =RIGHT(E47,4) -> 2026 | H47: 2026 | I47: =H47<2025 -> FALSE | K47: Yes | L47: English | M47: No
A48: Germany | B48: DEU | C48: =COUNTIF('IDA country list'!B$2:B$79,'WORKING VERSION'!B48) = 1 -> FALSE | D48: Strategy and Programme Plan 2017-2021 | E48: 2017-2021 | F48: https://unstats.un.org/unsd/dnss/docViewer.aspx?docID=3874 | G48: =RIGHT(E48,4) -> 2021 | H48: 2021 | I48: =H48<2025 -> TRUE | K48: Yes | L48: English | M48: No. There are costs outlined for each major statistical production area, but not broken down by activity.
A49: Djibouti | B49: DJI | C49: =COUNTIF('IDA country list'!B$2:B$79,'WORKING VERSION'!B49) = 1 -> TRUE | D49: Stratégie Nationale de Développement de la Statistique 2025-2029 | E49: 2025-2029 | F49: https://firebasestorage.googleapis.com/v0/b/instad-dj.appspot.com/o/SNDS%2F2025%2FRapport_final%20(SNDS3%202025-2029).pdf?alt=media&token=8f81ca01-e836-4578-bb6d-93ef208df5fa | G49: =RIGHT(E49,4) -> 2029 | H49: 2029 | I49: =H49<2025 -> FALSE | J49: TRUE | K49: Yes | L49: French | M49: Yes | N49: Yes | O49: Yes: 2025-2029 | P49: AM.2.1.3 is "Implement a strategy to better take gender into account in the production and analysis of statistics" with 10 line items within | Q49: 545000 | R49: USD | S49: Activité 2.1.1.9 : Réalisation d'enquêtes spécifiques auprès des ménages (violences fondées sur le genre) 400000; AM.2.1.3 Mettre en œuvre une stratégie pour une meilleure prise en compte du genre dans la production et l’analyse des statistiques 115000; Activité 2.1.3.11 : Collecte, la centralisation et la production des données statistique genre 30000
A50: Dominica | B50: DMA | C50: =COUNTIF('IDA country list'!B$2:B$79,'WORKING VERSION'!B50) = 1 -> TRUE | D50: Not available | G50: =RIGHT(E50,4) | I50: =H50<2025 -> TRUE | J50: TRUE
A51: Denmark | B51: DNK | C51: =COUNTIF('IDA country list'!B$2:B$79,'WORKING VERSION'!B51) = 1 -> FALSE | D51: Strategy 2025 | E51: 2025 | F51: https://www.dst.dk/en/Statistik/nyheder-analyser-publ/Publikationer/VisPub?cid=47814 | G51: =RIGHT(E51,4) -> 2025 | H51: 2025 | I51: =H51<2025 -> FALSE | K51: Yes | L51: English | M51: No
A52: Dominican Republic | B52: DOM | C52: =COUNTIF('IDA country list'!B$2:B$79,'WORKING VERSION'!B52) = 1 -> FALSE | D52: Plan Estratégico Institucional 2021-2024 | E52: 2021-2024 | F52: https://www.one.gob.do/sobre-nosotros/plan-estrategico/ | G52: =RIGHT(E52,4) -> 2024 | H52: 2024 | I52: =H52<2025 -> TRUE | K52: Yes | L52: Spanish | M52: No
A53: Algeria | B53: DZA | C53: =COUNTIF('IDA country list'!B$2:B$79,'WORKING VERSION'!B53) = 1 -> FALSE | D53: Stratégie Nationale de Développement de la Statistique 2017-19 | E53: 2017-2019 | F53: Not available | G53: =RIGHT(E53,4) -> 2019 | H53: 2019 | I53: =H53<2025 -> TRUE | K53: No
A54: Ecuador | B54: ECU | C54: =COUNTIF('IDA country list'!B$2:B$79,'WORKING VERSION'!B54) = 1 -> FALSE | D54: Programa Nacional de Estadística 2021-2025 | E54: 2021-2025 | F54: https://www.ecuadorencifras.gob.ec/documentos/web-inec/Sistema_Estadistico_Nacional/Planificacion_Estadistica/Programa_Nacional_de_Estadistica_2021-2025.pdf | G54: =RIGHT(E54,4) -> 2025 | H54: 2025 | I54: =H54<2025 -> FALSE | K54: Yes | L54: Spanish | M54: No
A55: Egypt | B55: EGY | C55: =COUNTIF('IDA country list'!B$2:B$79,'WORKING VERSION'!B55) = 1 -> FALSE | D55: National Strategy of Statistics 2017 - 21 | E55: 2017-2021 | F55: Not available | G55: =RIGHT(E55,4) -> 2021 | H55: 2021 | I55: =H55<2025 -> TRUE | K55: No
A56: Eritrea | B56: ERI | C56: =COUNTIF('IDA country list'!B$2:B$79,'WORKING VERSION'!B56) = 1 -> TRUE | I56: =H56<2025 -> TRUE | J56: TRUE
A57: Spain | B57: ESP | C57: =COUNTIF('IDA country list'!B$2:B$79,'WORKING VERSION'!B57) = 1 -> FALSE | D57: Royal Decree 1110/2020, of December 15, which approves the Plan National Statistician 2021-2024. | E57: 2021-2024 | F57: https://www.boe.es/boe/dias/2020/12/30/pdfs/BOE-A-2020-17283.pdf | G57: =RIGHT(E57,4) -> 2024 | H57: 2024 | I57: =H57<2025 -> TRUE | K57: Yes | L57: Spanish | M57: Yes - not in table form, but budget needed for financing each statistical operation is listed below each activity description | N57: Yes | O57: Budget isn't broken down by year | P57: Operation 8752: Statistics of Voluntary Interruptions of Pregnancy (budget: 328.08 thousand euros) (p. 147); Operation 8793: Statistics of Social Assistance of Article 27 to Women Victims of Gender Violence (budget: 60.16 thousand euros) (p. 153); Operation 8797: Statistics on Autonomous Resources on Violence Against Women (budget: 34.25 thousand euros) (p. 154); Operation 8798: Statistics of Victims of Violence against Women by Gender Reason (budget: 76.80 thousand euros) (p. 154); Operation 8825: Monitoring System by Telematic Means of Removal Measures in the Field of Gender Violence (budget: 33.20 thousand euros) (p. 156); Operation 8826: Statistics of the Comprehensive Monitoring System in Cases of Gender Violence (budget: 259.61 thousand euros) (p. 156-157); Operation 8832: Statistics on Domestic Violence and Gender Violence (budget: 185.54 thousand euros) (p. 158); Operation 8919: Telephone Service for Information and Legal Advice on Gender Violence (budget: 75.20 thousand euros) (p. 169); Operation 8920: Telephone Service for Attention and Protection for Victims of Gender Violence (budget: 33.20 thousand euros) (p. 169); Operation 8921: Macro-survey on Violence Against women (budget: 18.75 thousand euros) (p. 169-170); Operation 8932: Women and Men in Spain (budget: 358.65 thousand euros) (p. 173); Operation 8938: European Survey on Gender Violence (budget: 1386.79 thousand euros) (p. 174-175) | Q57: 2850230 | R57: EUR | S57: Operation 8793: Statistics of Social Assistance of Article 27 to Women Victims of Gender Violence (budget: 60.16 thousand euros) (p. 153); Operation 8797: Statistics on Autonomous Resources on Violence Against Women (budget: 34.25 thousand euros) (p. 154); Operation 8798: Statistics of Victims of Violence against Women by Gender Reason (budget: 76.80 thousand euros) (p. 154); Operation 8825: Monitoring System by Telematic Means of Removal Measures in the Field of Gender Violence (budget: 33.20 thousand euros) (p. 156); Operation 8826: Statistics of the Comprehensive Monitoring System in Cases of Gender Violence (budget: 259.61 thousand euros) (p. 156-157); Operation 8832: Statistics on Domestic Violence and Gender Violence (budget: 185.54 thousand euros) (p. 158); Operation 8919: Telephone Service for Information and Legal Advice on Gender Violence (budget: 75.20 thousand euros) (p. 169); Operation 8920: Telephone Service for Attention and Protection for Victims of Gender Violence (budget: 33.20 thousand euros) (p. 169); Operation 8921: Macro-survey on Violence Against women (budget: 18.75 thousand euros) (p. 169-170); Operation 8932: Women and Men in Spain (budget: 358.65 thousand euros) (p. 173); Operation 8938: European Survey on Gender Violence (budget: 1386.79 thousand euros) (p. 174-175) | T57: No
A58: Estonia | B58: EST | C58: =COUNTIF('IDA country list'!B$2:B$79,'WORKING VERSION'!B58) = 1 -> FALSE | D58: Development Plan of Statistics Estonia 2018-2022 | E58: 2023-2030 | F58: https://www.stat.ee/en/statistics-estonia/about-us/strategy | G58: =RIGHT(E58,4) -> 2030 | H58: 2030 | I58: =H58<2025 -> FALSE | K58: Yes | L58: English | M58: No
A59: Ethiopia | B59: ETH | C59: =COUNTIF('IDA country list'!B$2:B$79,'WORKING VERSION'!B59) = 1 -> TRUE | D59: National Strategy for the Development of Statistics 2021-2026 | E59: 2021-2026 | F59: http://www.statsethiopia.gov.et/wp-content/uploads/2024/02/ETHIOPIAN-STATISTICS-DEVELOPMENT-PROGRAM-ESDP-E.F.Y.-2016-2018-2024-2026-G.C..pdf | G59: 2026 | H59: 2026 | I59: =H59<2025 -> FALSE | K59: Yes | L59: English | M59: Yes | N59: Yes | O59: Yes: 2015/16-2019/20 | P59: Sub-theme 2.6 - Gender - 2.6.1: Mainstreaming gender data into surveys and censuses; 2.6.2: Conducting Time-Use Surveys; 2.6.3: Mining gender data from different surveys conducted so far; 2.6.4: Strengthening the functions of the Gender Mainstreaming Directorate; 2.6.5: Conducting Gender Asset Gap Survey | Q59: 1673542 | R59: USD | S59: 2.6.1: Mainstreaming gender data into surveys and censuses - $0 USD; 2.6.2: Conducting Time-Use Surveys - $617275 USD; 2.6.3: Mining gender data from different surveys conducted so far - $157,500 USD; 2.6.4: Strengthening the functions of the Gender Mainstreaming Directorate - $0 USD; 2.6.5: Conducting Gender Asset Gap Survey - $898767 USD | T59: Yes
A60: Finland | B60: FIN | C60: =COUNTIF('IDA country list'!B$2:B$79,'WORKING VERSION'!B60) = 1 -> FALSE | D60: Development strategy for the statistical ecosystem 2024-2026 | E60: 2024-2026 | F60: https://stat.fi/media/uploads/org/tilastotoimi/tilastoekosysteemin_kehittamislinjaukset_2024-2026-en.pdf | G60: =RIGHT(E60,4) -> 2026 | H60: 2026 | I60: =H60<2025 -> FALSE | K60: Yes | L60: English (page translated) | M60: No
A61: Fiji | B61: FJI | C61: =COUNTIF('IDA country list'!B$2:B$79,'WORKING VERSION'!B61) = 1 -> TRUE | D61: Not available | G61: =RIGHT(E61,4) | I61: =H61<2025 -> TRUE | J61: TRUE
A62: France | B62: FRA | C62: =COUNTIF('IDA country list'!B$2:B$79,'WORKING VERSION'!B62) = 1 -> FALSE | D62: Horizon: An Ambitious Strategy for INSEE 2016-2025 | E62: 2016-2025 | F62: https://www.insee.fr/en/statistiques/fichier/4195175/INSEE-2025-en.pdf | G62: =RIGHT(E62,4) -> 2025 | H62: 2025 | I62: =H62<2025 -> FALSE | K62: Yes | L62: English | M62: No
A63: Micronesia, Fed Sts. | B63: FSM | C63: =COUNTIF('IDA country list'!B$2:B$79,'WORKING VERSION'!B63) = 1 -> TRUE | D63: Not available | G63: =RIGHT(E63,4) | I63: =H63<2025 -> TRUE | J63: TRUE
A64: Gabon | B64: GAB | C64: =COUNTIF('IDA country list'!B$2:B$79,'WORKING VERSION'!B64) = 1 -> FALSE | D64: STRATÉGIE NATIONALE DE DÉVELOPPEMENT DE LA STATISTIQUE 2023-2025 | E64: 2023-2025 | F64: https://instatgabon.org/uploads/SNDS%202023-2025_VF%20.pdf | G64: =RIGHT(E64,4) -> 2025 | H64: 2025 | I64: =H64<2025 -> FALSE | K64: Yes | L64: French | M64: Yes | N64: Yes | O64: Yes: 2011-2015 | P64: Operation 14.9 - "Carrying out KAP and HIV seroprevalence surveys among sex workers" (p. 37) | Q64: 45000000 | R64: FCFA | S64: Operation 14.9 - 45 million FCFA | T64: Yes
A65: United Kingdom | B65: GBR | C65: =COUNTIF('IDA country list'!B$2:B$79,'WORKING VERSION'!B65) = 1 -> FALSE | D65: Strategic Business Plan 2020-2025 | E65: 2020-2025 | F65: https://uksa.statisticsauthority.gov.uk/wp-content/uploads/2020/07/ONS-Business-Plan-2020.pdf | G65: =RIGHT(E65,4) -> 2025 | H65: 2025 | I65: =H65<2025 -> FALSE | K65: Yes | L65: English | M65: Yes | N65: No
A66: Georgia | B66: GEO | C66: =COUNTIF('IDA country list'!B$2:B$79,'WORKING VERSION'!B66) = 1 -> FALSE | D66: National Strategy for the Development of the Official Statistics 2024-2027 | E66: 2024-2027 | F66: https://www.geostat.ge/media/63066/%E1%83%A1%E1%83%A2%E1%83%A0%E1%83%90%E1%83%A2%E1%83%94%E1%83%92%E1%83%98%E1%83%90-2024-2027_eng.pdf | G66: =RIGHT(E66,4) -> 2027 | H66: 2027 | I66: =H66<2025 -> FALSE | K66: Yes | L66: English | M66: No
A67: Ghana | B67: GHA | C67: =COUNTIF('IDA country list'!B$2:B$79,'WORKING VERSION'!B67) = 1 -> TRUE | D67: National Strategy for the Development of Statistics Ghana 2018-2022 | E67: 2018-2022 | F67: https://statsghana.gov.gh/gssmain/storage/img/NSDS%20II%20Ghana_Revised_16.03.18.pdf | G67: =RIGHT(E67,4) -> 2022 | H67: 2022 | I67: =H67<2025 -> TRUE | J67: TRUE | K67: Yes | L67: English | M67: Yes | N67: Yes | O67: Yes: 2018-2022 | P67: Activity 5.1.24: Capture gender disaggregated data in relation to age, urban and rural land transactions in 2017-2018 to satisfy data requirements of policy-makers (p. 46); Activity 5.3.6: Hold annual statistical literacy & advocacy programmes on gender statistics (p. 49) | Q67: 223475 | R67: USD | S67: Activity 5.1.24: $177,600; Activity 5.3.6: $45,875 | T67: No
A68: Ghana | B68: GHA | C68: =COUNTIF('IDA country list'!B$2:B$79,'WORKING VERSION'!B68) = 1 -> TRUE | D68: Five Year Strategic Plan for Gender Statistics | E68: 2018-2022 | F68: https://www.mogcsp.gov.gh/mdocs-posts/five-year-strategic-plan-for-gender-statistics/ | G68: =RIGHT(E68,4) -> 2022 | H68: 2022 | I68: =H68<2025 -> TRUE | J68: TRUE | K68: Yes | L68: English | M68: Yes | N68: Yes | O68: Yes: 2018-2022 | P68: Yes, entire budget tables are devoted to gender activities (see pg. 86-111) | Q68: 26627778 | R68: USD | S68: Yes, broken down by every distinct goal and objective. | T68: Unsure
A69: Guinea | B69: GIN | C69: =COUNTIF('IDA country list'!B$2:B$79,'WORKING VERSION'!B69) = 1 -> TRUE | D69: Stratégie Nationale de Développement de la Statistique 2016-2020 | E69: 2016-2020 | F69: https://www.stat-guinee.org/images/Documents/Publications/Textes/SNDS 2016-2020.pdf | G69: =RIGHT(E69,4) -> 2020 | H69: 2020 | I69: =H69<2025 -> TRUE | J69: TRUE | K69: Yes | L69: French | M69: Yes | N69: Yes | O69: Yes: 2016-2020 | P69: Activity 4.2.1: Take into account the needs for disaggregated data in the development of plans for the design and use of surveys and censuses; Activity 4.2.2: Strengthen gender and regional data analysis. (p. 58) | Q69: 324000000 | R69: GNF | S69: Activity 4.2.1: 162000000; Activity 4.2.2: 162000000 | T69: Yes
A70: The Gambia | B70: GMB | C70: =COUNTIF('IDA country list'!B$2:B$79,'WORKING VERSION'!B70) = 1 -> TRUE | D70: National Strategy for the Development of Statistics (NSDS III) of the Gambia 2024-2028 | E70: 2024-2028 | F70: https://www.gbosdata.org/downloads-file/526-national-strategy-for-the-development-of-stati | G70: =RIGHT(E70,4) -> 2028 | H70: 2028 | I70: =H70<2025 -> FALSE | K70: Yes | L70: English | M70: Yes | N70: No
A71: Guinea-Bissau | B71: GNB | C71: =COUNTIF('IDA country list'!B$2:B$79,'WORKING VERSION'!B71) = 1 -> TRUE | D71: Stratégie Nationale de Développement de la Statistique 2018-2020 | E71: 2018-2020 | F71: https://paris21.org/sites/default/files/2018-10/guinee-bissau_SNDS_Resume_FR_print_final.pdf | G71: =RIGHT(E71,4) -> 2020 | H71: 2020 | I71: =H71<2025 -> TRUE | J71: TRUE | K71: Yes | L71: French | M71: No. There are costs outlined for each stratgic axis, but not broken down by activity. | N71: No
A72: Equatorial Guinea | B72: GNQ | C72: =COUNTIF('IDA country list'!B$2:B$79,'WORKING VERSION'!B72) = 1 -> FALSE | D72: Estrategia Nacional de Desarrollo de la Estadística de Guinea Ecuatorial 2022-2026 | E72: 2022-2026 | F72: https://inege.gq/wp-content/uploads/2023/09/ENDE-2022-2026.pdf | G72: =RIGHT(E72,4) -> 2026 | H72: 2026 | I72: =H72<2025 -> FALSE | K72: Yes | L72: Spanish | M72: Yes | N72: Yes | O72: Yes: 2022-2026 | P72: 1.1.8.1 - Preparation of gender statistics through administrative records; 1.1.8.2 - Conducting a National Survey on the socioeconomic situation of women in Equatorial Guinea; 1.1.8.3 - Carrying out a National Survey on the situation of the Elderly in Equatorial Guinea; 1.1.8.4 - Carrying out a study on the child protection environment in Equatorial Guinea; 1.1.8.5 - Conducting a Survey on vulnerable households; 1.1.8.6 - Carrying out and disseminating a review and compilation study of customary law and positive law on women's rights concerning: a) marital regime, divorce and parental authority; b) trend of land and property ownership; c) physical mobility; d) the different typologies of violence; 1.1.8.7 - Promotion and dissemination of research that analyzes the situation of women in terms of access and representation in different public decision-making spaces (state powers, political parties, private sector, etc.); 1.1.8.8 - Conducting research on the impact of economic policies on the lives of women, the conditions of their labor insertion and their contributions to the national economy; 1.1.8.9 - Carrying out a study on the impact of public policies on the lives of families in Equatorial Guinea; 1.1.8.10 - Carrying out a study on the impact of Covid -19 on homes; 1.1.8.11 - Study -Identification of children in precarious situations in educational centers nationwide (p. 89-90); 2.2.4.6 - Development of a framework of gender statistical indicators (p. 98); 3.2.1.8 - Organization of a training workshop on methodologies, concepts and definitions related to gender statistics (p. 101) | Q72: 365000000 | R72: CFA | S72: 1.1.8.1 - 30 million francs 1.1.8.2 - 50 million francs 1.1.8.3 - 40 million francs 1.1.8.4 - 15 million francs 1.1.8.5 - 50 million francs 1.1.8.6 - 30 million francs 1.1.8.7 - 25 million francs 1.1.8.8 - 25 million francs 1.1.8.9 - 20 million francs 1.1.8.10 - 50 million francs 1.1.8.11 - 20 million francs 2.2.4.6 - 5 million francs 3.2.1.8 - 5 million francs | T72: Yes
A73: Greece | B73: GRC | C73: =COUNTIF('IDA country list'!B$2:B$79,'WORKING VERSION'!B73) = 1 -> FALSE | D73: ELSTAT Hellenistic Statistical Programme 2023-2025 | E73: 2023-2025 | F73: https://www.statistics.gr/documents/20181/301385/Statistical_Program_2023_2025_en.pdf/75edd155-199b-8924-0a11-8ba36d715418 | G73: =RIGHT(E73,4) -> 2025 | H73: 2025 | I73: =H73<2025 -> FALSE | K73: Yes | L73: English | M73: No (broad budget but not broken down in detail) | N73: No | O73: Yes: 2022 | P73: No
A74: Grenada | B74: GRD | C74: =COUNTIF('IDA country list'!B$2:B$79,'WORKING VERSION'!B74) = 1 -> TRUE | D74: Not available | G74: =RIGHT(E74,4) | I74: =H74<2025 -> TRUE | J74: TRUE
A75: Greenland | B75: GRL | C75: =COUNTIF('IDA country list'!B$2:B$79,'WORKING VERSION'!B75) = 1 -> FALSE | D75: Not available | G75: =RIGHT(E75,4) | I75: =H75<2025 -> TRUE
A76: Guatemala | B76: GTM | C76: =COUNTIF('IDA country list'!B$2:B$79,'WORKING VERSION'!B76) = 1 -> FALSE | D76: PLAN ESTRATEGICO INSTITUCIONAL -PEI 2024-2028 | E76: 2024-2028 | F76: https://www.ine.gob.gt/sistema/uploads/2024/07/04/202407041908069Odm3oxU9mTY58hkborwzylm7MJop05q.pdf | G76: =RIGHT(E76,4) -> 2028 | H76: 2028 | I76: =H76<2025 -> FALSE | K76: Yes | L76: Spanish | M76: No (broad budget on main statistical products) | N76: No | O76: Yes: 2018:2022 | T76: No
A77: Guyana | B77: GUY | C77: =COUNTIF('IDA country list'!B$2:B$79,'WORKING VERSION'!B77) = 1 -> TRUE | D77: Not available | G77: =RIGHT(E77,4) | I77: =H77<2025 -> TRUE | J77: TRUE
A78: Hong Kong SAR, China | B78: HKG | C78: =COUNTIF('IDA country list'!B$2:B$79,'WORKING VERSION'!B78) = 1 -> FALSE | D78: Open Data Plan 2022-2024 | E78: 2022-2024 | F78: https://www.censtatd.gov.hk/en/FileManager/Annual%20Open%20Data%20Plan%20for%202022-2024.pdf | G78: =RIGHT(E78,4) -> 2024 | H78: 2024 | I78: =H78<2025 -> TRUE | K78: Yes | L78: English | M78: No
A79: Honduras | B79: HND | C79: =COUNTIF('IDA country list'!B$2:B$79,'WORKING VERSION'!B79) = 1 -> TRUE | D79: Estrategia Nacional para el Desarrollo Estadístico de Honduras 2023-2033 | E79: 2023-2033 | F79: https://ine.gob.hn/wp-content/uploads/2025/08/Estrategia-ENDEH-Honduras-2023-2033.pdf | G79: =RIGHT(E79,4) -> 2033 | H79: 2033 | I79: =H79<2025 -> FALSE | K79: Yes | L79: Spanish | M79: Yes | N79: Yes | O79: No | P79: Entire table and activity level over 10 years (not by year) | Q79: 43912500 | R79: HNL | S79: A.E.4.1.1. Fortalecer las capacidades técnicas de unidades institucionales en igualdad y equidad de Género para la producción y análisis de estadísticas desagregadas por sus categorías de género. 6,000,000.00; A.E.4.1.2. Elaborar e implementar protocolos y/o guías para análisis con enfoque de género para los diferentes sectores del país.7300000; A.E.4.1.3. Diseñar y ejecutar un plan para asistencia técnica desde la cooperación nacional e internacional para la producción de estadísticas desagregadas por género que permitan generar políticas de igualdad y equidad de género. 11625000; A.E.4.1.4. Uniformar formatos, unidades y sistemas de captura de información estadística en cada una de las secretarías de estado para el registro de estadísticas desagregadas por sus categorías de género el SEN del país 3875000.00; A.E.4.1.5. Priorizar variables, indicadores y generar las operaciones estadísticas desagregadas por sus categorías de género. 3487500; A.E.4.1.6. Implementar un Sistema de Información Inter operativo e Interconectado funcionando con indicadores priorizados, mecanismos y herramientas para generar datos del Sistema Estadístico Nacional, vinculados a los sistemas de estadísticas desagregadas por sus categorías de género 11625000 | T79: No
A80: Croatia | B80: HRV | C80: =COUNTIF('IDA country list'!B$2:B$79,'WORKING VERSION'!B80) = 1 -> FALSE | D80: Development Strategy of Official Statistics of the Republic of Croatia 2021-2030 | E80: 2021-2030 | F80: https://dzs.gov.hr/UserDocsImages/dokumenti/Dokumenti/DEVELOPMENT%20STRATEGY%20OF%20OFFICIAL%20STATISTICS%20RH%202021-2030_NN%2029-2022_ENG.pdf | G80: =RIGHT(E80,4) -> 2030 | H80: 2030 | I80: =H80<2025 -> FALSE | K80: Yes | L80: English | M80: No
A81: Haiti | B81: HTI | C81: =COUNTIF('IDA country list'!B$2:B$79,'WORKING VERSION'!B81) = 1 -> TRUE | D81: National Strategy for the Development of Statistics 2016-21 | E81: 2016-2021 | F81: Not available | G81: =RIGHT(E81,4) -> 2021 | H81: 2021 | I81: =H81<2025 -> TRUE | J81: TRUE | K81: No
A82: Hungary | B82: HUN | C82: =COUNTIF('IDA country list'!B$2:B$79,'WORKING VERSION'!B82) = 1 -> FALSE | D82: Not available | G82: =RIGHT(E82,4) | I82: =H82<2025 -> TRUE
A83: Indonesia | B83: IDN | C83: =COUNTIF('IDA country list'!B$2:B$79,'WORKING VERSION'!B83) = 1 -> FALSE | D83: National Statistical Plan 2020 – 2024 | E83: 2020-2024 | F83: https://www.bps.go.id/website/fileMenu/Renstra-BPS-2020-2024.pdf | G83: =RIGHT(E83,4) -> 2024 | H83: 2024 | I83: =H83<2025 -> TRUE | K83: Yes | L83: Indonesian | M83: Yes | N83: Yes | O83: Yes: 2020-2024 | P83: Component of activity 2896: Number of Gender Equality and Gender Empowerment Indicators compiled (p.102) | Q83: Not specified (there is only a total for the broader activity as a whole, which includes many non-gender-focused elements) | T83: No
A84: India | B84: IND | C84: =COUNTIF('IDA country list'!B$2:B$79,'WORKING VERSION'!B84) = 1 -> FALSE | D84: Five Year Vision 2019-2024 | E84: 2019-2024 | F84: https://www.mospi.gov.in/sites/default/files/main_menu/parliament_matters/Vision_2024_of_MoSPI.pdf | G84: =RIGHT(E84,4) -> 2024 | H84: 2024 | I84: =H84<2025 -> TRUE | K84: Yes | L84: English | M84: No
A85: Ireland | B85: IRL | C85: =COUNTIF('IDA country list'!B$2:B$79,'WORKING VERSION'!B85) = 1 -> FALSE | D85: Statement of Strategy 2020-2023 | E85: 2020-2023 | F85: https://www.cso.ie/en/media/csoie/releasespublications/documents/corporatepublications/CSO_Statement_Of_Strategy_2020-2023.pdf | G85: =RIGHT(E85,4) -> 2023 | H85: 2023 | I85: =H85<2025 -> TRUE | K85: Yes | L85: English | M85: No
A86: Iran, Islamic Rep. | B86: IRN | C86: =COUNTIF('IDA country list'!B$2:B$79,'WORKING VERSION'!B86) = 1 -> FALSE | D86: Not available | G86: =RIGHT(E86,4) | I86: =H86<2025 -> TRUE
A87: Iraq | B87: IRQ | C87: =COUNTIF('IDA country list'!B$2:B$79,'WORKING VERSION'!B87) = 1 -> FALSE | D87: Statistical Master plan 2010-14 | E87: 2010-2014 | F87: https://cosit.gov.iq/images/pdf/workplan2023.pdf | G87: =RIGHT(E87,4) -> 2014 | H87: 2014 | I87: =H87<2025 -> TRUE | K87: Yes | L87: Arabic | M87: No
A88: Iceland | B88: ISL | C88: =COUNTIF('IDA country list'!B$2:B$79,'WORKING VERSION'!B88) = 1 -> FALSE | D88: Not available | G88: =RIGHT(E88,4) | I88: =H88<2025 -> TRUE
A89: Israel | B89: ISR | C89: =COUNTIF('IDA country list'!B$2:B$79,'WORKING VERSION'!B89) = 1 -> FALSE | D89: Not available | G89: =RIGHT(E89,4) | I89: =H89<2025 -> TRUE
A90: Italy | B90: ITA | C90: =COUNTIF('IDA country list'!B$2:B$79,'WORKING VERSION'!B90) = 1 -> FALSE | D90: Not available | G90: =RIGHT(E90,4) | I90: =H90<2025 -> TRUE
A91: Jamaica | B91: JAM | C91: =COUNTIF('IDA country list'!B$2:B$79,'WORKING VERSION'!B91) = 1 -> FALSE | D91: Not available | G91: =RIGHT(E91,4) | I91: =H91<2025 -> TRUE
A92: Jordan | B92: JOR | C92: =COUNTIF('IDA country list'!B$2:B$79,'WORKING VERSION'!B92) = 1 -> FALSE | D92: National Strategy for Development of Statistics 2018-22 | E92: 2018-2022 | F92: https://paris21.org/sites/default/files/2019-05/JPRDAN_NSDS 18-22.pdf | G92: =RIGHT(E92,4) -> 2022 | H92: 2022 | I92: =H92<2025 -> TRUE | K92: Yes | L92: English | M92: Yes | N92: No | O92: Yes: 2018-2022 | T92: Column called "Party/Parties responsible for implementation" - unclear if related to funding though (p. 31). There is a funding source column in the work plan table starting on page 38.
A93: Japan | B93: JPN | C93: =COUNTIF('IDA country list'!B$2:B$79,'WORKING VERSION'!B93) = 1 -> FALSE | D93: Not available | G93: =RIGHT(E93,4) | I93: =H93<2025 -> TRUE
A94: Kazakhstan | B94: KAZ | C94: =COUNTIF('IDA country list'!B$2:B$79,'WORKING VERSION'!B94) = 1 -> FALSE | D94: Not available | G94: =RIGHT(E94,4) | I94: =H94<2025 -> TRUE
A95: Kenya | B95: KEN | C95: =COUNTIF('IDA country list'!B$2:B$79,'WORKING VERSION'!B95) = 1 -> TRUE | D95: National Strategy for the Development of Statistics 2023-2027 | E95: 2023-2027 | F95: https://www.knbs.or.ke/wp-content/uploads/2024/03/Kenya-National-Bureau-of-Statistics-Strategic-Plan-2023-2027.pdf | G95: =RIGHT(E95,4) -> 2027 | H95: 2027 | I95: =H95<2025 -> FALSE | K95: Yes | L95: English | M95: Yes | N95: Yes | O95: Yes: 2019-2023 | P95: Stratetgic Objective 2.2, activity 7: Enhance data disaggregation (p. 51); Survey #23: Time Use, Survey #25: VAW, Survey #26: Social Institution and Gender Index, (p. 58) | Q95: 690000000 | R95: KSH | S95: Enhance data disaggregation - 80 million Ksh; Survey #23: Time Use - 60 million Ksh, Survey #25: VAW - 400 million Ksh, Survey #26: Social Institution and Gender Index - 150 million Ksh (p. 58) | T95: No
A96: Kenya | B96: KEN | C96: =COUNTIF('IDA country list'!B$2:B$79,'WORKING VERSION'!B96) = 1 -> TRUE | D96: Strategic Plan 2023-2027 | E96: 2023-2027 | F96: https://www.knbs.or.ke/wp-content/uploads/2024/03/Kenya-National-Bureau-of-Statistics-Strategic-Plan-2023-2027.pdf | G96: =RIGHT(E96,4) -> 2027 | H96: 2027 | I96: =H96<2025 -> FALSE | J96: TRUE | K96: Yes | L96: English | M96: Yes | N96: Yes | O96: 2023/24 - 2027/28 | P96: In Annex I: "Mainstream ADA, HIV/AIDS issues, Disability, Gender and National Cohesion and National Values" as Key Activity. In Annex II, "Conduct Gender in Trade Study" "Conduct Gender and Corruption Study" "Gender Statistics Sector Plan" etc. | Q96: 5.7500002e+15 | R96: KSH
A97: Kyrgyz Republic | B97: KGZ | C97: =COUNTIF('IDA country list'!B$2:B$79,'WORKING VERSION'!B97) = 1 -> TRUE | D97: Medium-Term Program for the Development of Official Statistics of the Kyrgyz Republic for 2022-2026 | E97: 2022-2026 | F97: https://stat.gov.kg/media/files/51deb952-67b3-4a65-84d0-d89b76ffce48.pdf#:~:text=The%20Medium%2Dterm%20Program%20for%20Development%20of%20Official,the%20Kyrgyz%20Republic%20of%2031%20October%202018. | G97: =RIGHT(E97,4) -> 2026 | H97: 2026 | I97: =H97<2025 -> FALSE | K97: Yes | L97: English | M97: No | T97: Yes
A98: Cambodia | B98: KHM | C98: =COUNTIF('IDA country list'!B$2:B$79,'WORKING VERSION'!B98) = 1 -> TRUE | D98: Cambodia National Strategy for the Development of Statistics 2019 - 2023 | E98: 2019-2023 | F98: https://www.nis.gov.kh/nis/NSDS/NSDS book.pdf | G98: =RIGHT(E98,4) -> 2023 | H98: 2023 | I98: =H98<2025 -> TRUE | J98: TRUE | K98: Yes | L98: English | M98: Yes | N98: Yes | O98: Yes: 2019-2023 | P98: Activity 34: Women and Men in Cambodia Booklet (pg. 85) | Q98: 30000 | R98: USD | S98: Women and Men in Cambodia Booklet: 15,000 in 2020, and 15,000 in 2022 | T98: No
A99: Kiribati | B99: KIR | C99: =COUNTIF('IDA country list'!B$2:B$79,'WORKING VERSION'!B99) = 1 -> TRUE | D99: Kiribati National Strategy for the Development of Statistics 2024–2030 | E99: 2024-2030 | F99: https://spccfpstore1.blob.core.windows.net/digitallibrary-docs/files/d6/d6bc2354a12f54ea223c6878199c9a6d.pdf?sv=2015-12-11&sr=b&sig=60pAM5ERWEYfNF4fvpLwwE%2BE6BMfYibL3GHdutfTs1k%3D&se=2026-05-04T16%3A40%3A26Z&sp=r&rscc=public%2C%20max-age%3D864000%2C%20max-stale%3D86400&rsct=application%2Fpdf&rscd=inline%3B%20filename%3D%22Kiribati_NSDS_2024_2030.pdf%22 | G99: =RIGHT(E99,4) -> 2030 | H99: 2030 | I99: =H99<2025 -> FALSE | J99: TRUE | K99: No | L99: English | M99: No | N99: No
A100: St. Kitts and Nevis | B100: KNA | C100: =COUNTIF('IDA country list'!B$2:B$79,'WORKING VERSION'!B100) = 1 -> FALSE | D100: Not available | G100: =RIGHT(E100,4) | I100: =H100<2025 -> TRUE
...

Sheet Gender Statistics plans
A1: country | B1: iso3c | C1: link
A2: Kenya | B2: KEN | C2: https://www.knbs.or.ke/gender-sector-statistics-plan/
A3: Ghana | B3: GHA | C3: https://www.mogcsp.gov.gh/mdocs-posts/five-year-strategic-plan-for-gender-statistics/
A4: Maldives | B4: MDV | C4: https://statisticsmaldives.gov.mv/mbs/wp-content/uploads/2024/10/NSDGS.pdf
A5: Dominican Republic | B5: DOM | C5: https://www.one.gob.do/publicaciones/2022/estrategia-de-estadisticas-de-genero-de-la-republica-dominicana-2021-2024/
A6: Paraguay | B6: PRY | C6: https://www.ine.gov.py/resumen/175/estrategia-de-estadisticas-de-genero-paraguay-2021--2025
A7: Georgia | B7: GEO | C7: https://www.geostat.ge/en/modules/categories/716/strategy-for-gender-statistics-2021-2023
A8: Southern Africa Development Community | B8: SADC | C8: https://www.sadc.int/sites/default/files/2024-02/SADC%20Gender%20Statistics%20Strategy%202022-30_EN.pdf
A9: Pacific Community | B9: PAC | C9: https://data.unwomen.org/sites/default/files/documents/Publications/Pacific-Roadmap-Gender-Statistics.pdf

Sheet IDA country list
A1: country | B1: Code | C1: Region | D1: Income group | E1: Lending category
A2: Afghanistan | B2: AFG | C2: Middle East, North Africa, Afghanistan & Pakistan | D2: Low income | E2: IDA | J2: AFG | K2: =J2=H2 -> FALSE | N2: BGD
A3: Bangladesh | B3: BGD | C3: South Asia | D3: Lower middle income | E3: IDA | H3: BDI | J3: BDI | K3: =J3=H3 -> TRUE | N3: BLZ
A4: Belize | B4: BLZ | C4: Latin America & Caribbean | D4: Upper middle income | E4: Blend | H4: BEN | J4: BEN | K4: =J4=H4 -> TRUE | N4: BEN
A5: Benin | B5: BEN | C5: Sub-Saharan Africa | D5: Lower middle income | E5: IDA | H5: BFA | J5: BFA | K5: =J5=H5 -> TRUE | N5: BTN
A6: Bhutan | B6: BTN | C6: South Asia | D6: Lower middle income | E6: IDA | H6: BGD | J6: BGD | K6: =J6=H6 -> TRUE | N6: BFA
A7: Burkina Faso | B7: BFA | C7: Sub-Saharan Africa | D7: Low income | E7: IDA | H7: BLZ | J7: BLZ | K7: =J7=H7 -> TRUE | N7: BDI
A8: Burundi | B8: BDI | C8: Sub-Saharan Africa | D8: Low income | E8: IDA | H8: BTN | J8: BTN | K8: =J8=H8 -> TRUE | N8: CPV
A9: Cabo Verde | B9: CPV | C9: Sub-Saharan Africa | D9: Upper middle income | E9: Blend | H9: CAF | J9: CAF | K9: =J9=H9 -> TRUE | N9: KHM
A10: Cambodia | B10: KHM | C10: East Asia & Pacific | D10: Lower middle income | E10: IDA | H10: CIV | J10: CIV | K10: =J10=H10 -> TRUE | N10: CMR
A11: Cameroon | B11: CMR | C11: Sub-Saharan Africa | D11: Lower middle income | E11: Blend | H11: CMR | J11: CMR | K11: =J11=H11 -> TRUE | N11: CAF
A12: Central African Republic | B12: CAF | C12: Sub-Saharan Africa | D12: Low income | E12: IDA | H12: COD | J12: COD | K12: =J12=H12 -> TRUE | N12: TCD
A13: Chad | B13: TCD | C13: Sub-Saharan Africa | D13: Low income | E13: IDA | H13: COG | J13: COG | K13: =J13=H13 -> TRUE | N13: COD
A14: Comoros | B14: COM | C14: Sub-Saharan Africa | D14: Lower middle income | E14: IDA | J14: COM | K14: =J14=H14 -> FALSE | N14: COG
A15: Congo, Dem. Rep. | B15: COD | C15: Sub-Saharan Africa | D15: Low income | E15: IDA | H15: CPV | J15: CPV | K15: =J15=H15 -> TRUE | N15: CIV
A16: Congo, Rep. | B16: COG | C16: Sub-Saharan Africa | D16: Lower middle income | E16: Blend | H16: DJI | J16: DJI | K16: =J16=H16 -> TRUE | N16: DJI
A17: Côte d’Ivoire | B17: CIV | C17: Sub-Saharan Africa | D17: Lower middle income | E17: Blend | H17: DMA | J17: DMA | K17: =J17=H17 -> TRUE | N17: DMA
A18: Djibouti | B18: DJI | C18: Middle East, North Africa, Afghanistan & Pakistan | D18: Lower middle income | E18: IDA | J18: ERI | K18: =J18=H18 -> FALSE | N18: SWZ
A19: Dominica | B19: DMA | C19: Latin America & Caribbean | D19: Upper middle income | E19: Blend | H19: ETH | J19: ETH | K19: =J19=H19 -> TRUE | N19: ETH
A20: Eritrea | B20: ERI | C20: Sub-Saharan Africa | D20: Low income | E20: IDA | H20: FJI | J20: FJI | K20: =J20=H20 -> TRUE | N20: FJI
A21: Eswatini | B21: SWZ | C21: Sub-Saharan Africa | D21: Lower middle income | E21: Blend | H21: FSM | J21: FSM | K21: =J21=H21 -> TRUE | N21: GHA
A22: Ethiopia | B22: ETH | C22: Sub-Saharan Africa | E22: IDA | H22: GHA | J22: GHA | K22: =J22=H22 -> TRUE | N22: GRD
A23: Fiji | B23: FJI | C23: East Asia & Pacific | D23: Upper middle income | E23: Blend | H23: GIN | J23: GIN | K23: =J23=H23 -> TRUE | N23: GIN
A24: Gambia, The | B24: GMB | C24: Sub-Saharan Africa | D24: Low income | E24: IDA | H24: GMB | J24: GMB | K24: =J24=H24 -> TRUE | N24: GNB
A25: Ghana | B25: GHA | C25: Sub-Saharan Africa | D25: Lower middle income | E25: IDA | H25: GNB | J25: GNB | K25: =J25=H25 -> TRUE | N25: GUY
A26: Grenada | B26: GRD | C26: Latin America & Caribbean | D26: Upper middle income | E26: Blend | H26: GRD | J26: GRD | K26: =J26=H26 -> TRUE | N26: HTI
A27: Guinea | B27: GIN | C27: Sub-Saharan Africa | D27: Lower middle income | E27: IDA | H27: GUY | J27: GUY | K27: =J27=H27 -> TRUE | N27: HND
A28: Guinea-Bissau | B28: GNB | C28: Sub-Saharan Africa | D28: Low income | E28: IDA | H28: HND | J28: HND | K28: =J28=H28 -> TRUE | N28: KEN
A29: Guyana | B29: GUY | C29: Latin America & Caribbean | D29: High income | E29: IDA | H29: HTI | J29: HTI | K29: =J29=H29 -> TRUE | N29: KIR
A30: Haiti | B30: HTI | C30: Latin America & Caribbean | D30: Lower middle income | E30: IDA | H30: KEN | J30: KEN | K30: =J30=H30 -> TRUE | N30: XKX
A31: Honduras | B31: HND | C31: Latin America & Caribbean | D31: Lower middle income | E31: IDA | H31: KGZ | J31: KGZ | K31: =J31=H31 -> TRUE | N31: KGZ
A32: Kenya | B32: KEN | C32: Sub-Saharan Africa | D32: Lower middle income | E32: Blend | H32: KHM | J32: KHM | K32: =J32=H32 -> TRUE | N32: LAO
A33: Kiribati | B33: KIR | C33: East Asia & Pacific | D33: Lower middle income | E33: IDA | H33: KIR | J33: KIR | K33: =J33=H33 -> TRUE | N33: LSO
A34: Kosovo | B34: XKX | C34: Europe & Central Asia | D34: Upper middle income | E34: IDA | H34: LAO | J34: LAO | K34: =J34=H34 -> TRUE | N34: LBR
... A53: Papua New Guinea | B53: PNG | C53: East Asia & Pacific | D53: Lower middle income | E53: Blend | H53: RWA | J53: RWA | K53: =J53=H53 -> TRUE | N53: SEN
A54: Rwanda | B54: RWA | C54: Sub-Saharan Africa | D54: Low income | E54: IDA | J54: SDN | K54: =J54=H54 -> FALSE | N54: SLE
A55: Samoa | B55: WSM | C55: East Asia & Pacific | D55: Upper middle income | E55: IDA | H55: SEN | J55: SEN | K55: =J55=H55 -> TRUE | N55: SLB
A56: São Tomé and Príncipe | B56: STP | C56: Sub-Saharan Africa | D56: Lower middle income | E56: IDA | H56: SLB | J56: SLB | K56: =J56=H56 -> TRUE | N56: SOM
A57: Senegal | B57: SEN | C57: Sub-Saharan Africa | D57: Lower middle income | E57: IDA | H57: SLE | J57: SLE | K57: =J57=H57 -> TRUE | N57: SSD
A58: Sierra Leone | B58: SLE | C58: Sub-Saharan Africa | D58: Low income | E58: IDA | H58: SOM | J58: SOM | K58: =J58=H58 -> TRUE | N58: LKA
A59: Solomon Islands | B59: SLB | C59: East Asia & Pacific | D59: Lower middle income | E59: IDA | H59: SSD | J59: SSD | K59: =J59=H59 -> TRUE | N59: LCA
A60: Somalia | B60: SOM | C60: Sub-Saharan Africa | D60: Low income | E60: IDA | H60: STP | J60: STP | K60: =J60=H60 -> TRUE | N60: VCT
A61: South Sudan | B61: SSD | C61: Sub-Saharan Africa | D61: Low income | E61: IDA | H61: SUR | J61: SUR | K61: =J61=H61 -> TRUE | N61: SUR
A62: Sri Lanka | B62: LKA | C62: South Asia | D62: Lower middle income | E62: IDA | H62: SWZ | J62: SWZ | K62: =J62=H62 -> TRUE | N62: SYR
A63: St. Lucia | B63: LCA | C63: Latin America & Caribbean | D63: Upper middle income | E63: Blend | H63: SYR | J63: SYR | K63: =J63=H63 -> TRUE | N63: TJK
A64: St. Vincent and the Grenadines | B64: VCT | C64: Latin America & Caribbean | D64: Upper middle income | E64: Blend | H64: TCD | J64: TCD | K64: =J64=H64 -> TRUE | N64: TZA
A65: Sudan | B65: SDN | C65: Sub-Saharan Africa | D65: Low income | E65: IDA | H65: TGO | J65: TGO | K65: =J65=H65 -> TRUE | N65: GMB
A66: Suriname | B66: SUR | C66: Latin America & Caribbean | D66: Upper middle income | E66: Blend | H66: TJK | J66: TJK | K66: =J66=H66 -> TRUE | N66: TLS
... A79: Zimbabwe | B79: ZWE | C79: Sub-Saharan Africa | D79: Lower middle income | E79: Blend | H79: ZWE | J79: ZWE | K79: =J79=H79 -> TRUE | N79: SDN
